[
  {"district_code":"UP01","district_name":"Agra","district_name_hi":"आगरा"},
  {"district_code":"UP02","district_name":"Aligarh","district_name_hi":"अलीगढ़"},
  {"district_code":"UP03","district_name":"Allahabad","district_name_hi":"इलाहाबाद"},
  {"district_code":"UP04","district_name":"Ambedkar Nagar","district_name_hi":"अंबेडकर नगर"},
  {"district_code":"UP05","district_name":"Amethi","district_name_hi":"अमेठी"},
  {"district_code":"UP06","district_name":"Amroha","district_name_hi":"अमरोहा"},
  {"district_code":"UP07","district_name":"Auraiya","district_name_hi":"औरैया"},
  {"district_code":"UP08","district_name":"Azamgarh","district_name_hi":"आजमगढ़"},
  {"district_code":"UP09","district_name":"Baghpat","district_name_hi":"बागपत"},
  {"district_code":"UP10","district_name":"Bahraich","district_name_hi":"बहराइच"},
  {"district_code":"UP11","district_name":"Ballia","district_name_hi":"बलिया"},
  {"district_code":"UP12","district_name":"Balrampur","district_name_hi":"बलरामपुर"},
  {"district_code":"UP13","district_name":"Banda","district_name_hi":"बांदा"},
  {"district_code":"UP14","district_name":"Barabanki","district_name_hi":"बाराबंकी"},
  {"district_code":"UP15","district_name":"Bareilly","district_name_hi":"बरेली"},
  {"district_code":"UP16","district_name":"Basti","district_name_hi":"बस्ती"},
  {"district_code":"UP17","district_name":"Bijnor","district_name_hi":"बिजनौर"},
  {"district_code":"UP18","district_name":"Budaun","district_name_hi":"बदायूं"},
  {"district_code":"UP19","district_name":"Bulandshahr","district_name_hi":"बुलंदशहर"},
  {"district_code":"UP20","district_name":"Chandauli","district_name_hi":"चंदौली"},
  {"district_code":"UP21","district_name":"Chitrakoot","district_name_hi":"चित्रकूट"},
  {"district_code":"UP22","district_name":"Deoria","district_name_hi":"देवरिया"},
  {"district_code":"UP23","district_name":"Etah","district_name_hi":"एटा"},
  {"district_code":"UP24","district_name":"Etawah","district_name_hi":"इटावा"},
  {"district_code":"UP25","district_name":"Faizabad","district_name_hi":"फैजाबाद"},
  {"district_code":"UP26","district_name":"Farrukhabad","district_name_hi":"फर्रुखाबाद"},
  {"district_code":"UP27","district_name":"Fatehpur","district_name_hi":"फतेहपुर"},
  {"district_code":"UP28","district_name":"Firozabad","district_name_hi":"फिरोजाबाद"},
  {"district_code":"UP29","district_name":"Gautam Buddha Nagar","district_name_hi":"गौतम बुद्ध नगर"},
  {"district_code":"UP30","district_name":"Ghaziabad","district_name_hi":"गाजियाबाद"},
  {"district_code":"UP31","district_name":"Ghazipur","district_name_hi":"गाजीपुर"},
  {"district_code":"UP32","district_name":"Gonda","district_name_hi":"गोंडा"},
  {"district_code":"UP33","district_name":"Gorakhpur","district_name_hi":"गोरखपुर"},
  {"district_code":"UP34","district_name":"Hamirpur","district_name_hi":"हमीरपुर"},
  {"district_code":"UP35","district_name":"Hapur","district_name_hi":"हापुड़"},
  {"district_code":"UP36","district_name":"Hardoi","district_name_hi":"हरदोई"},
  {"district_code":"UP37","district_name":"Hathras","district_name_hi":"हाथरस"},
  {"district_code":"UP38","district_name":"Jalaun","district_name_hi":"जालौन"},
  {"district_code":"UP39","district_name":"Jaunpur","district_name_hi":"जौनपुर"},
  {"district_code":"UP40","district_name":"Jhansi","district_name_hi":"झांसी"},
  {"district_code":"UP41","district_name":"Kannauj","district_name_hi":"कन्नौज"},
  {"district_code":"UP42","district_name":"Kanpur Dehat","district_name_hi":"कानपुर देहात"},
  {"district_code":"UP43","district_name":"Kanpur Nagar","district_name_hi":"कानपुर नगर"},
  {"district_code":"UP44","district_name":"Kasganj","district_name_hi":"कासगंज"},
  {"district_code":"UP45","district_name":"Kaushambi","district_name_hi":"कौशाम्बी"},
  {"district_code":"UP46","district_name":"Kushinagar","district_name_hi":"कुशीनगर"},
  {"district_code":"UP47","district_name":"Lakhimpur Kheri","district_name_hi":"लखीमपुर खीरी"},
  {"district_code":"UP48","district_name":"Lalitpur","district_name_hi":"ललितपुर"},
  {"district_code":"UP49","district_name":"Lucknow","district_name_hi":"लखनऊ"},
  {"district_code":"UP50","district_name":"Maharajganj","district_name_hi":"महाराजगंज"},
  {"district_code":"UP51","district_name":"Mahoba","district_name_hi":"महोबा"},
  {"district_code":"UP52","district_name":"Mainpuri","district_name_hi":"मैनपुरी"},
  {"district_code":"UP53","district_name":"Mathura","district_name_hi":"मथुरा"},
  {"district_code":"UP54","district_name":"Mau","district_name_hi":"मऊ"},
  {"district_code":"UP55","district_name":"Meerut","district_name_hi":"मेरठ"},
  {"district_code":"UP56","district_name":"Mirzapur","district_name_hi":"मिर्ज़ापुर"},
  {"district_code":"UP57","district_name":"Moradabad","district_name_hi":"मुरादाबाद"},
  {"district_code":"UP58","district_name":"Muzaffarnagar","district_name_hi":"मुज़फ्फरनगर"},
  {"district_code":"UP59","district_name":"Pilibhit","district_name_hi":"पीलीभीत"},
  {"district_code":"UP60","district_name":"Pratapgarh","district_name_hi":"प्रतापगढ़"},
  {"district_code":"UP61","district_name":"Rae Bareli","district_name_hi":"रायबरेली"},
  {"district_code":"UP62","district_name":"Rampur","district_name_hi":"रामपुर"},
  {"district_code":"UP63","district_name":"Saharanpur","district_name_hi":"सहारनपुर"},
  {"district_code":"UP64","district_name":"Sambhal","district_name_hi":"संभल"},
  {"district_code":"UP65","district_name":"Sant Kabir Nagar","district_name_hi":"संत कबीर नगर"},
  {"district_code":"UP66","district_name":"Bhadohi","district_name_hi":"भदोही"},
  {"district_code":"UP67","district_name":"Shahjahanpur","district_name_hi":"शाहजहांपुर"},
  {"district_code":"UP68","district_name":"Shamli","district_name_hi":"शामली"},
  {"district_code":"UP69","district_name":"Shravasti","district_name_hi":"श्रावस्ती"},
  {"district_code":"UP70","district_name":"Siddharthnagar","district_name_hi":"सिद्धार्थनगर"},
  {"district_code":"UP71","district_name":"Sitapur","district_name_hi":"सीतापुर"},
  {"district_code":"UP72","district_name":"Sonbhadra","district_name_hi":"सोनभद्र"},
  {"district_code":"UP73","district_name":"Sultanpur","district_name_hi":"सुल्तानपुर"},
  {"district_code":"UP74","district_name":"Unnao","district_name_hi":"उन्नाव"},
  {"district_code":"UP75","district_name":"Varanasi","district_name_hi":"वाराणसी"}
]
